synthguard/__init__.py
synthguard/data_preprocessor.py
synthguard/helper_functions.py
synthguard/input_handler.py
synthguard/privacy_report_generator.py
synthguard/quality_report_generator.py
synthguard/synthetic_data_generator.py
synthguard-0.0.1.dist-info/LICENSE
synthguard-0.0.1.dist-info/METADATA
synthguard-0.0.1.dist-info/WHEEL
synthguard-0.0.1.dist-info/top_level.txt
synthguard-0.0.1.dist-info/RECORD
